uiautomation/__init__.py
uiautomation/py.typed
uiautomation/uiautomation.py
uiautomation/version.py
uiautomation/bin/UIAutomationClient_VC140_X64.dll
uiautomation/bin/UIAutomationClient_VC140_X86.dll
uiautomation-2.0.27.data/scripts/automation.py
uiautomation-2.0.27.dist-info/LICENSE
uiautomation-2.0.27.dist-info/METADATA
uiautomation-2.0.27.dist-info/WHEEL
uiautomation-2.0.27.dist-info/top_level.txt
uiautomation-2.0.27.dist-info/RECORD
