Metadata-Version: 2.1
Name: uiautomation
Version: 2.0.27
Summary: Python UIAutomation for Windows
Home-page: https://github.com/yinkaisheng/Python-UIAutomation-for-Windows
Author: yinkaisheng
Author-email: yinkaisheng@foxmail.com
License: Apache 2.0
Keywords: windows ui automation uiautomation inspect
Platform: Windows Only
Classifier: Programming Language :: Python :: 3.4
Classifier: Programming Language :: Python :: 3.5
Classifier: Programming Language :: Python :: 3.6
Classifier: Programming Language :: Python :: 3.7
Classifier: Programming Language :: Python :: 3.8
Classifier: Programming Language :: Python :: 3.9
Classifier: Programming Language :: Python :: 3.10
Classifier: Programming Language :: Python :: 3.11
Classifier: Programming Language :: Python :: 3.12
License-File: LICENSE
Requires-Dist: comtypes >=1.2.1
